jobtools/__init__.py
jobtools/__main__.py
jobtools/arguments.py
jobtools/joblogger.py
jobtools/runner.py
jobtools-0.0.16.data/scripts/jobtools
jobtools-0.0.16.data/scripts/pyrunit
jobtools-0.0.16.dist-info/LICENSE.md
jobtools-0.0.16.dist-info/METADATA
jobtools-0.0.16.dist-info/WHEEL
jobtools-0.0.16.dist-info/top_level.txt
jobtools-0.0.16.dist-info/RECORD
