Metadata-Version: 2.1
Name: jobtools
Version: 0.0.16
Summary: Facilitates the use of Python from the command line
Home-page: https://github.com/santiagxf/jobtools
Author: Facundo Santiago
Classifier: Programming Language :: Python :: 3
Classifier: License :: OSI Approved :: MIT License
Classifier: Operating System :: OS Independent
Requires-Python: >=3.6
License-File: LICENSE.md
Requires-Dist: PyYAML
